{
    "type": "pixel",
    "description": "Converted 16x16 PNG to JSON",
    "width": 16,
    "height": 16,
    "sprite": [
        [
            "#518f45",
            "#538d44",
            "#90acb0",
            "#549141",
            "#45784b",
            "#478140",
            "#436b4c",
            "#335345",
            "#738ca0",
            "#17191e",
            "#3a3d41",
            "#373741",
            "#373840",
            "#303238",
            "#33363d",
            "#34353d"
        ],
        [
            "#396539",
            "#4a8347",
            "#8daab7",
            "#5a964e",
            "#4d8640",
            "#46704a",
            "#416f46",
            "#375749",
            "#748fa0",
            "#221d26",
            "#3d3f45",
            "#34373c",
            "#35353e",
            "#36383f",
            "#36363f",
            "#30323b"
        ],
        [
            "#32593a",
            "#498144",
            "#4f8943",
            "#8faab5",
            "#3c663d",
            "#447046",
            "#2b5439",
            "#3a604d",
            "#8197a7",
            "#2a2a33",
            "#24272f",
            "#383b42",
            "#373940",
            "#393b42",
            "#383941",
            "#35353d"
        ],
        [
            "#36554d",
            "#5c924d",
            "#569049",
            "#8da7b3",
            "#3b6935",
            "#406a43",
            "#3f6746",
            "#2e523e",
            "#7590a2",
            "#313339",
            "#2a2b36",
            "#3a3d43",
            "#3a3c42",
            "#36373e",
            "#393a42",
            "#3a3a42"
        ],
        [
            "#315149",
            "#3e7936",
            "#5d9653",
            "#91aabe",
            "#2a5623",
            "#44724a",
            "#446d4c",
            "#335b3f",
            "#738d9c",
            "#3a3f3f",
            "#2c3037",
            "#26272f",
            "#2a2d34",
            "#393a42",
            "#36373e",
            "#33353c"
        ],
        [
            "#458543",
            "#59944d",
            "#4d8940",
            "#588f56",
            "#9db6c4",
            "#3b6d35",
            "#3e693e",
            "#3c614b",
            "#7390a0",
            "#3c3d42",
            "#353942",
            "#252730",
            "#33353a",
            "#393b41",
            "#353940",
            "#393a42"
        ],
        [
            "#41703f",
            "#4d844b",
            "#558f4a",
            "#49843e",
            "#90adb2",
            "#285034",
            "#365c46",
            "#345844",
            "#79949f",
            "#474b4e",
            "#3b4144",
            "#21242a",
            "#2b2d34",
            "#34373f",
            "#393c42",
            "#393c42"
        ],
        [
            "#467843",
            "#5b944d",
            "#58954e",
            "#548f46",
            "#89a7a5",
            "#2c583e",
            "#456d54",
            "#7793a6",
            "#303035",
            "#41434a",
            "#404246",
            "#252930",
            "#2d2d35",
            "#3b3a41",
            "#33353c",
            "#3b3d46"
        ],
        [
            "#3b713b",
            "#508847",
            "#458139",
            "#447a4e",
            "#88a7aa",
            "#3b6a3c",
            "#38633a",
            "#829ead",
            "#31363b",
            "#41474d",
            "#353841",
            "#23272f",
            "#2d3038",
            "#393a43",
            "#383a41",
            "#393a41"
        ],
        [
            "#599450",
            "#558d48",
            "#548b45",
            "#569043",
            "#89a7a9",
            "#35662a",
            "#7194a0",
            "#3a3d44",
            "#394047",
            "#4c5255",
            "#30323b",
            "#292e35",
            "#2d2f37",
            "#3a3a42",
            "#33333c",
            "#37383f"
        ],
        [
            "#548d49",
            "#538b43",
            "#568d43",
            "#4b8253",
            "#7693a4",
            "#3c5f6a",
            "#7693a0",
            "#2c3438",
            "#484f53",
            "#353d3f",
            "#35383f",
            "#23272e",
            "#32353d",
            "#35363f",
            "#3a3a44",
            "#383941"
        ],
        [
            "#5b9651",
            "#5c924d",
            "#4c8449",
            "#416a4e",
            "#627f8d",
            "#7495a3",
            "#262c34",
            "#51595c",
            "#4c5357",
            "#2f343a",
            "#3c4148",
            "#2d3238",
            "#2e313a",
            "#33353e",
            "#383a41",
            "#36383f"
        ],
        [
            "#49813a",
            "#4a8244",
            "#4f8347",
            "#457346",
            "#6e8a9c",
            "#2e323d",
            "#51575d",
            "#50585b",
            "#353b43",
            "#3b3d48",
            "#24272e",
            "#2f323d",
            "#36373e",
            "#363840",
            "#34353c",
            "#3a3b44"
        ],
        [
            "#4d8744",
            "#456b43",
            "#4a6f4b",
            "#7c99a6",
            "#32373f",
            "#4d545a",
            "#4d5358",
            "#383e46",
            "#353b45",
            "#353942",
            "#23272f",
            "#35373f",
            "#36373e",
            "#393a43",
            "#34353c",
            "#3b3d44"
        ],
        [
            "#4c794b",
            "#7694a7",
            "#648390",
            "#373d45",
            "#545c5f",
            "#444b4f",
            "#383f45",
            "#3e434b",
            "#353943",
            "#25272f",
            "#2e3039",
            "#3d3f46",
            "#393c42",
            "#3a3a43",
            "#3c3d45",
            "#36363f"
        ],
        [
            "#6d8b9a",
            "#2f3b42",
            "#3e404d",
            "#565e63",
            "#4d5459",
            "#3a4146",
            "#373d46",
            "#333740",
            "#353b41",
            "#292c36",
            "#34353f",
            "#35363f",
            "#3b3d45",
            "#373940",
            "#36363d",
            "#383b42"
        ]
    ],
    "colors": [
        "#17191e",
        "#21242a",
        "#221d26",
        "#23272e",
        "#23272f",
        "#24272e",
        "#24272f",
        "#25272f",
        "#252730",
        "#252930",
        "#26272f",
        "#262c34",
        "#285034",
        "#292c36",
        "#292e35",
        "#2a2a33",
        "#2a2b36",
        "#2a2d34",
        "#2a5623",
        "#2b2d34",
        "#2b5439",
        "#2c3037",
        "#2c3438",
        "#2c583e",
        "#2d2d35",
        "#2d2f37",
        "#2d3038",
        "#2d3238",
        "#2e3039",
        "#2e313a",
        "#2e323d",
        "#2e523e",
        "#2f323d",
        "#2f343a",
        "#2f3b42",
        "#303035",
        "#303238",
        "#30323b",
        "#313339",
        "#31363b",
        "#315149",
        "#32353d",
        "#32373f",
        "#32593a",
        "#33333c",
        "#33353a",
        "#33353c",
        "#33353e",
        "#33363d",
        "#333740",
        "#335345",
        "#335b3f",
        "#34353c",
        "#34353d",
        "#34353f",
        "#34373c",
        "#34373f",
        "#345844",
        "#35353d",
        "#35353e",
        "#35363f",
        "#35373f",
        "#35383f",
        "#353841",
        "#353940",
        "#353942",
        "#353943",
        "#353b41",
        "#353b43",
        "#353b45",
        "#353d3f",
        "#35662a",
        "#36363d",
        "#36363f",
        "#36373e",
        "#36383f",
        "#363840",
        "#36554d",
        "#365c46",
        "#373741",
        "#37383f",
        "#373840",
        "#373940",
        "#373d45",
        "#373d46",
        "#375749",
        "#383941",
        "#383a41",
        "#383b42",
        "#383e46",
        "#383f45",
        "#38633a",
        "#393a41",
        "#393a42",
        "#393a43",
        "#393b41",
        "#393b42",
        "#393c42",
        "#394047",
        "#396539",
        "#3a3a42",
        "#3a3a43",
        "#3a3a44",
        "#3a3b44",
        "#3a3c42",
        "#3a3d41",
        "#3a3d43",
        "#3a3d44",
        "#3a3f3f",
        "#3a4146",
        "#3a604d",
        "#3b3a41",
        "#3b3d44",
        "#3b3d45",
        "#3b3d46",
        "#3b3d48",
        "#3b4144",
        "#3b6935",
        "#3b6a3c",
        "#3b6d35",
        "#3b713b",
        "#3c3d42",
        "#3c3d45",
        "#3c4148",
        "#3c5f6a",
        "#3c614b",
        "#3c663d",
        "#3d3f45",
        "#3d3f46",
        "#3e404d",
        "#3e434b",
        "#3e693e",
        "#3e7936",
        "#3f6746",
        "#404246",
        "#406a43",
        "#41434a",
        "#41474d",
        "#416a4e",
        "#416f46",
        "#41703f",
        "#436b4c",
        "#444b4f",
        "#446d4c",
        "#447046",
        "#44724a",
        "#447a4e",
        "#456b43",
        "#456d54",
        "#457346",
        "#45784b",
        "#458139",
        "#458543",
        "#46704a",
        "#467843",
        "#474b4e",
        "#478140",
        "#484f53",
        "#49813a",
        "#498144",
        "#49843e",
        "#4a6f4b",
        "#4a8244",
        "#4a8347",
        "#4b8253",
        "#4c5255",
        "#4c5357",
        "#4c794b",
        "#4c8449",
        "#4d5358",
        "#4d5459",
        "#4d545a",
        "#4d844b",
        "#4d8640",
        "#4d8744",
        "#4d8940",
        "#4f8347",
        "#4f8943",
        "#50585b",
        "#508847",
        "#51575d",
        "#51595c",
        "#518f45",
        "#538b43",
        "#538d44",
        "#545c5f",
        "#548b45",
        "#548d49",
        "#548f46",
        "#549141",
        "#558d48",
        "#558f4a",
        "#565e63",
        "#568d43",
        "#569043",
        "#569049",
        "#588f56",
        "#58954e",
        "#59944d",
        "#599450",
        "#5a964e",
        "#5b944d",
        "#5b9651",
        "#5c924d",
        "#5d9653",
        "#627f8d",
        "#648390",
        "#6d8b9a",
        "#6e8a9c",
        "#7194a0",
        "#738ca0",
        "#738d9c",
        "#7390a0",
        "#748fa0",
        "#7495a3",
        "#7590a2",
        "#7693a0",
        "#7693a4",
        "#7694a7",
        "#7793a6",
        "#79949f",
        "#7c99a6",
        "#8197a7",
        "#829ead",
        "#88a7aa",
        "#89a7a5",
        "#89a7a9",
        "#8da7b3",
        "#8daab7",
        "#8faab5",
        "#90acb0",
        "#90adb2",
        "#91aabe",
        "#9db6c4"
    ]
}