{
    "type": "pixel",
    "description": "Converted 16x16 PNG to JSON",
    "width": 16,
    "height": 16,
    "sprite": [
        [
            "#4b923b",
            "#3d743d",
            "#577887",
            "#507280",
            "#436d3e",
            "#3a693c",
            "#498a40",
            "#406c3e",
            "#497348",
            "#89a6bb",
            "#3f6071",
            "#3d606e",
            "#3c633b",
            "#3e6b3f",
            "#3c6b3b",
            "#466b78"
        ],
        [
            "#529744",
            "#4c9040",
            "#3d6b41",
            "#3a6245",
            "#3e733a",
            "#4a8a40",
            "#43733f",
            "#406e3d",
            "#3e6e41",
            "#34534e",
            "#9db6cc",
            "#396b3d",
            "#457141",
            "#427f38",
            "#46863d",
            "#3a6d3c"
        ],
        [
            "#448a38",
            "#3f7b3a",
            "#376f33",
            "#39544e",
            "#3f6d3c",
            "#427142",
            "#477547",
            "#407042",
            "#385945",
            "#31554b",
            "#3e773a",
            "#92a9bf",
            "#3a6435",
            "#3c6e3b",
            "#3c6e3c",
            "#9ab2c1"
        ],
        [
            "#3f7939",
            "#467f3b",
            "#426e41",
            "#364a4a",
            "#355349",
            "#3d6a3f",
            "#3c6e3e",
            "#325d3c",
            "#448839",
            "#468d3b",
            "#3d6b3d",
            "#385c4c",
            "#8eaab1",
            "#8daeb3",
            "#89a7b1",
            "#437d36"
        ],
        [
            "#3b5e44",
            "#3a6240",
            "#366134",
            "#394a47",
            "#36554b",
            "#2f4a43",
            "#2a4e3a",
            "#4a9140",
            "#3d8735",
            "#4e9441",
            "#4f9043",
            "#39633e",
            "#9cb7bd",
            "#416a48",
            "#3e6c42",
            "#447d40"
        ],
        [
            "#334f4d",
            "#38524c",
            "#3d6a3a",
            "#3b683b",
            "#365650",
            "#394d49",
            "#407142",
            "#3a7437",
            "#4b913c",
            "#559b49",
            "#4d903f",
            "#386d38",
            "#3b624c",
            "#91b0b6",
            "#467341",
            "#407439"
        ],
        [
            "#474549",
            "#3c6c3c",
            "#3e6b3d",
            "#426c3e",
            "#3d6b3b",
            "#474147",
            "#406c45",
            "#43793e",
            "#417c39",
            "#498c3b",
            "#427f3e",
            "#3b7439",
            "#3c6051",
            "#98babe",
            "#2e5c2c",
            "#37693d"
        ],
        [
            "#3b3e3f",
            "#366837",
            "#467b3c",
            "#3d703a",
            "#3d683a",
            "#3a3b3d",
            "#314a48",
            "#406841",
            "#457843",
            "#477d44",
            "#488144",
            "#3a663b",
            "#38544e",
            "#48784b",
            "#92b2b4",
            "#1f422e"
        ],
        [
            "#3e6a3c",
            "#3e6d3d",
            "#599146",
            "#5b934e",
            "#457751",
            "#3d6a45",
            "#314447",
            "#2f4947",
            "#3b643f",
            "#3d6744",
            "#39633a",
            "#324f4a",
            "#364a49",
            "#39534e",
            "#93afc5",
            "#163123"
        ],
        [
            "#619853",
            "#558a47",
            "#4f8b44",
            "#599149",
            "#548e47",
            "#5b954c",
            "#39404a",
            "#333a41",
            "#313841",
            "#424a51",
            "#303a40",
            "#3c414b",
            "#444b55",
            "#464e57",
            "#314b48",
            "#8eadaf"
        ],
        [
            "#619a54",
            "#58924b",
            "#4b823e",
            "#497f4f",
            "#528a43",
            "#5b8d55",
            "#363e45",
            "#7f868d",
            "#778187",
            "#707881",
            "#7b868f",
            "#737d86",
            "#687377",
            "#424a51",
            "#3a604c",
            "#99b7b2"
        ],
        [
            "#518946",
            "#558d46",
            "#528d45",
            "#59904f",
            "#558846",
            "#393c4e",
            "#7a8189",
            "#747e86",
            "#7d8a90",
            "#747f85",
            "#79838b",
            "#6e777f",
            "#4e5c64",
            "#4a515b",
            "#54904d",
            "#548e48"
        ],
        [
            "#5f9953",
            "#599549",
            "#798a7f",
            "#818e8b",
            "#788583",
            "#343846",
            "#62707a",
            "#5a676e",
            "#68747d",
            "#59676f",
            "#627079",
            "#616f77",
            "#535d68",
            "#465058",
            "#518d43",
            "#538a44"
        ],
        [
            "#687571",
            "#7e8985",
            "#78887f",
            "#7d8f84",
            "#5d974d",
            "#3a414c",
            "#61707a",
            "#49545e",
            "#68717d",
            "#3c4b50",
            "#505c64",
            "#69777e",
            "#4c5963",
            "#3c464f",
            "#67a458",
            "#5e9853"
        ],
        [
            "#89958f",
            "#818f89",
            "#73837c",
            "#5b914c",
            "#5a944e",
            "#353b4a",
            "#5e6a73",
            "#6d7b84",
            "#5b6971",
            "#626f79",
            "#5f6e77",
            "#5d6872",
            "#4c5565",
            "#37494f",
            "#5d9c4c",
            "#5a9450"
        ],
        [
            "#869391",
            "#798781",
            "#4f8841",
            "#5f9850",
            "#57914a",
            "#3c434f",
            "#657481",
            "#465059",
            "#464e5a",
            "#47515c",
            "#54636d",
            "#5b6d73",
            "#436d4a",
            "#51874b",
            "#376a4a",
            "#5e9750"
        ]
    ],
    "colors": [
        "#163123",
        "#1f422e",
        "#2a4e3a",
        "#2e5c2c",
        "#2f4947",
        "#2f4a43",
        "#303a40",
        "#313841",
        "#314447",
        "#314a48",
        "#314b48",
        "#31554b",
        "#324f4a",
        "#325d3c",
        "#333a41",
        "#334f4d",
        "#343846",
        "#34534e",
        "#353b4a",
        "#355349",
        "#363e45",
        "#364a49",
        "#364a4a",
        "#36554b",
        "#365650",
        "#366134",
        "#366837",
        "#37494f",
        "#37693d",
        "#376a4a",
        "#376f33",
        "#38524c",
        "#38544e",
        "#385945",
        "#385c4c",
        "#386d38",
        "#393c4e",
        "#39404a",
        "#394a47",
        "#394d49",
        "#39534e",
        "#39544e",
        "#39633a",
        "#39633e",
        "#396b3d",
        "#3a3b3d",
        "#3a414c",
        "#3a604c",
        "#3a6240",
        "#3a6245",
        "#3a6435",
        "#3a663b",
        "#3a693c",
        "#3a6d3c",
        "#3a7437",
        "#3b3e3f",
        "#3b5e44",
        "#3b624c",
        "#3b643f",
        "#3b683b",
        "#3b7439",
        "#3c414b",
        "#3c434f",
        "#3c464f",
        "#3c4b50",
        "#3c6051",
        "#3c633b",
        "#3c6b3b",
        "#3c6c3c",
        "#3c6e3b",
        "#3c6e3c",
        "#3c6e3e",
        "#3d606e",
        "#3d6744",
        "#3d683a",
        "#3d6a3a",
        "#3d6a3f",
        "#3d6a45",
        "#3d6b3b",
        "#3d6b3d",
        "#3d6b41",
        "#3d703a",
        "#3d743d",
        "#3d8735",
        "#3e6a3c",
        "#3e6b3d",
        "#3e6b3f",
        "#3e6c42",
        "#3e6d3d",
        "#3e6e41",
        "#3e733a",
        "#3e773a",
        "#3f6071",
        "#3f6d3c",
        "#3f7939",
        "#3f7b3a",
        "#406841",
        "#406c3e",
        "#406c45",
        "#406e3d",
        "#407042",
        "#407142",
        "#407439",
        "#416a48",
        "#417c39",
        "#424a51",
        "#426c3e",
        "#426e41",
        "#427142",
        "#427f38",
        "#427f3e",
        "#436d3e",
        "#436d4a",
        "#43733f",
        "#43793e",
        "#437d36",
        "#444b55",
        "#447d40",
        "#448839",
        "#448a38",
        "#457141",
        "#457751",
        "#457843",
        "#464e57",
        "#464e5a",
        "#465058",
        "#465059",
        "#466b78",
        "#467341",
        "#467b3c",
        "#467f3b",
        "#46863d",
        "#468d3b",
        "#474147",
        "#474549",
        "#47515c",
        "#477547",
        "#477d44",
        "#48784b",
        "#488144",
        "#49545e",
        "#497348",
        "#497f4f",
        "#498a40",
        "#498c3b",
        "#4a515b",
        "#4a8a40",
        "#4a9140",
        "#4b823e",
        "#4b913c",
        "#4b923b",
        "#4c5565",
        "#4c5963",
        "#4c9040",
        "#4d903f",
        "#4e5c64",
        "#4e9441",
        "#4f8841",
        "#4f8b44",
        "#4f9043",
        "#505c64",
        "#507280",
        "#51874b",
        "#518946",
        "#518d43",
        "#528a43",
        "#528d45",
        "#529744",
        "#535d68",
        "#538a44",
        "#54636d",
        "#548e47",
        "#548e48",
        "#54904d",
        "#558846",
        "#558a47",
        "#558d46",
        "#559b49",
        "#577887",
        "#57914a",
        "#58924b",
        "#59676f",
        "#59904f",
        "#599146",
        "#599149",
        "#599549",
        "#5a676e",
        "#5a944e",
        "#5a9450",
        "#5b6971",
        "#5b6d73",
        "#5b8d55",
        "#5b914c",
        "#5b934e",
        "#5b954c",
        "#5d6872",
        "#5d974d",
        "#5d9c4c",
        "#5e6a73",
        "#5e9750",
        "#5e9853",
        "#5f6e77",
        "#5f9850",
        "#5f9953",
        "#616f77",
        "#61707a",
        "#619853",
        "#619a54",
        "#626f79",
        "#627079",
        "#62707a",
        "#657481",
        "#67a458",
        "#68717d",
        "#687377",
        "#68747d",
        "#687571",
        "#69777e",
        "#6d7b84",
        "#6e777f",
        "#707881",
        "#737d86",
        "#73837c",
        "#747e86",
        "#747f85",
        "#778187",
        "#788583",
        "#78887f",
        "#79838b",
        "#798781",
        "#798a7f",
        "#7a8189",
        "#7b868f",
        "#7d8a90",
        "#7d8f84",
        "#7e8985",
        "#7f868d",
        "#818e8b",
        "#818f89",
        "#869391",
        "#89958f",
        "#89a6bb",
        "#89a7b1",
        "#8daeb3",
        "#8eaab1",
        "#8eadaf",
        "#91b0b6",
        "#92a9bf",
        "#92b2b4",
        "#93afc5",
        "#98babe",
        "#99b7b2",
        "#9ab2c1",
        "#9cb7bd",
        "#9db6cc"
    ]
}